{ \repo\: \mlm-master-platform\, \file\: \vip_Test.jsx\, \timestamp\: \2025-06-21T13:40:24Z\ }
{ "repo": "mlm-master-platform", "file": "vip_Test.jsx", "timestamp": "2025-06-21T13:52:06Z" }
{ "repo": "mlm-master-platform", "file": "vip_Test.jsx", "timestamp": "2025-06-21T14:06:45Z" }
{ "repo": "mlm-master-platform", "file": "vip_Test.jsx", "timestamp": "2025-06-23T09:38:10Z" }
{ "repo": "mlm-master-platform", "file": "vip_Test.jsx", "timestamp": "2025-06-23T09:39:31Z" }
{ "repo": "mlm-master-platform", "file": "vip_Test.jsx", "timestamp": "2025-06-23T09:42:47Z" }
